querymark/__init__.py
querymark-1.1.0.dist-info/licenses/LICENSE
querymark-1.1.0.dist-info/METADATA
querymark-1.1.0.dist-info/WHEEL
querymark-1.1.0.dist-info/top_level.txt
querymark-1.1.0.dist-info/RECORD
