Metadata-Version: 2.4
Name: querymark
Version: 1.1.0
Summary: Lightweight Python query builder for asyncpg. Use ? placeholders and querymark handles the $1, $2, $3 conversion.
Author: hlynurj
License: MIT
Project-URL: Homepage, https://github.com/hlynurj/querymark
Project-URL: Repository, https://github.com/hlynurj/querymark
Classifier: Development Status :: 5 - Production/Stable
Classifier: Intended Audience :: Developers
Classifier: License :: OSI Approved :: MIT License
Classifier: Programming Language :: Python :: 3
Classifier: Programming Language :: Python :: 3.9
Classifier: Programming Language :: Python :: 3.10
Classifier: Programming Language :: Python :: 3.11
Classifier: Programming Language :: Python :: 3.12
Requires-Python: >=3.9
License-File: LICENSE
Dynamic: license-file
